[
  {
    "type": "object",
    "label": "pool",
    "score": 0.861,
    "box": [
      22.61,
      419.27,
      454.05,
      502.41
    ]
  },
  {
    "type": "object",
    "label": "pool",
    "score": 0.854,
    "box": [
      40.72,
      761.17,
      449.41,
      875.84
    ]
  },
  {
    "type": "object",
    "label": "pool",
    "score": 0.846,
    "box": [
      31.2,
      210.04,
      452.72,
      325.32
    ]
  },
  {
    "type": "object",
    "label": "pool",
    "score": 0.84,
    "box": [
      25.69,
      970.41,
      447.89,
      1084.17
    ]
  },
  {
    "type": "object",
    "label": "task",
    "score": 0.802,
    "box": [
      142.0,
      1174.08,
      324.96,
      1262.12
    ]
  },
  {
    "type": "object",
    "label": "pool",
    "score": 0.737,
    "box": [
      39.64,
      32.98,
      430.1,
      121.2
    ]
  },
  {
    "type": "object",
    "label": "pool",
    "score": 0.721,
    "box": [
      40.28,
      583.08,
      434.61,
      669.28
    ]
  },
  {
    "type": "arrow",
    "label": "sequenceFlow",
    "score": 0.829,
    "box": [
      230.4,
      129.63,
      246.61,
      205.51
    ],
    "keypoints": [
      [
        239.46,
        130.12
      ],
      [
        238.51,
        205.03
      ]
    ]
  },
  {
    "type": "arrow",
    "label": "sequenceFlow",
    "score": 0.762,
    "box": [
      229.37,
      883.96,
      246.49,
      966.09
    ],
    "keypoints": [
      [
        238.4,
        884.43
      ],
      [
        238.4,
        965.61
      ]
    ]
  },
  {
    "type": "arrow",
    "label": "sequenceFlow",
    "score": 0.696,
    "box": [
      229.99,
      505.93,
      246.17,
      582.97
    ],
    "keypoints": [
      [
        238.08,
        506.41
      ],
      [
        239.03,
        582.49
      ]
    ]
  },
  {
    "type": "arrow",
    "label": "sequenceFlow",
    "score": 0.618,
    "box": [
      229.65,
      1094.7,
      245.95,
      1173.77
    ],
    "keypoints": [
      [
        237.8,
        1095.18
      ],
      [
        238.76,
        1173.29
      ]
    ]
  },
  {
    "type": "arrow",
    "label": "sequenceFlow",
    "score": 0.614,
    "box": [
      229.48,
      335.53,
      245.87,
      413.51
    ],
    "keypoints": [
      [
        237.67,
        336.01
      ],
      [
        238.64,
        413.03
      ]
    ]
  },
  {
    "type": "arrow",
    "label": "sequenceFlow",
    "score": 0.583,
    "box": [
      229.75,
      676.67,
      246.19,
      753.29
    ],
    "keypoints": [
      [
        238.42,
        677.15
      ],
      [
        238.42,
        752.82
      ]
    ]
  }
]